bidaf/__init__.py
bidaf/__main__.py
bidaf/layers/__init__.py
bidaf/layers/combine_outputs.py
bidaf/layers/context_to_query.py
bidaf/layers/highway_layer.py
bidaf/layers/merged_context.py
bidaf/layers/query_to_context.py
bidaf/layers/similarity_layer.py
bidaf/layers/span_begin.py
bidaf/layers/span_end.py
bidaf/models/__init__.py
bidaf/models/bidaf.py
bidaf/scripts/__init__.py
bidaf/scripts/accuracy_metric.py
bidaf/scripts/batch_generator.py
bidaf/scripts/data_generator.py
bidaf/scripts/loss_function.py
bidaf/scripts/magnitude.py
bidaf/scripts/multi_gpu_model.py
bidaf/scripts/postprocess.py
bidaf/scripts/preprocess.py
bidaf_keras-1.0.0.dist-info/METADATA
bidaf_keras-1.0.0.dist-info/RECORD
bidaf_keras-1.0.0.dist-info/WHEEL
bidaf_keras-1.0.0.dist-info/entry_points.txt
bidaf_keras-1.0.0.dist-info/top_level.txt
