Metadata-Version: 2.1
Name: bidaf-keras
Version: 1.0.0
Summary: Implementation of Bidirectional Attention Flow for Machine Comprehension in Keras 2
Home-page: https://github.com/ParikhKadam/bidaf-keras
Author: Kadam Parikh
Author-email: parikhkadam@gmail.com
License: MIT
Download-URL: https://github.com/ParikhKadam/bidaf-keras/archive/v-1.0.0.tar.gz
Platform: UNKNOWN
Classifier: Development Status :: 5 - Production/Stable
Classifier: License :: OSI Approved :: MIT License
Classifier: Programming Language :: Python :: 3
Classifier: Programming Language :: Python :: 3.6
Provides-Extra: cpu
Provides-Extra: gpu
Requires-Dist: pymagnitude
Requires-Dist: keras
Requires-Dist: tqdm
Requires-Dist: nltk
Provides-Extra: cpu
Requires-Dist: tensorflow; extra == 'cpu'
Provides-Extra: gpu
Requires-Dist: tensorflow-gpu; extra == 'gpu'
